pysorter/__init__.py
pysorter/__main__.py
pysorter/commandline.py
pysorter/filesystem.py
pysorter/filetypes.py
pysorter/oranize.py
pysorter/rules.py
pysorter/version.txt
pysorter/tests/__init__.py
pysorter/tests/conftest.py
pysorter/tests/helper.py
pysorter/tests/test_arguments.py
pysorter/tests/test_commandline.py
pysorter/tests/test_filesystem.py
pysorter/tests/test_patterns.py
pysorter/tests/test_rules.py
pysorter/tests/test_sorter.py
pysorter/tests/test_wildcard_patterns.py
pysorter-0.4.2.dist-info/DESCRIPTION.rst
pysorter-0.4.2.dist-info/METADATA
pysorter-0.4.2.dist-info/RECORD
pysorter-0.4.2.dist-info/WHEEL
pysorter-0.4.2.dist-info/entry_points.txt
pysorter-0.4.2.dist-info/metadata.json
pysorter-0.4.2.dist-info/top_level.txt
